{
  "meta": { "project": "BESS_Project_1", "source": "demo" },
  "tagMap": {
    "overall.current_energy_wh": 12500,
    "overall.soc_percent": 62.5,
    "overall.current_state": "Charge",
    "overall.current_strategy": "Pattern 1",

    "solar.v": 230.0,
    "solar.i": 12.4,
    "solar.p": 2850,
    "solar.e": 8200,

    "grid.v": 230.0,
    "grid.i": 6.2,
    "grid.p": 1420,
    "grid.e": 5400,

    "load.v": 230.0,
    "load.i": 18.1,
    "load.p": 4160,
    "load.e": 13200,

    "pack.1.v": 390.1,
    "pack.1.i": 8.2,
    "pack.1.soc": 63.0,
    "pack.1.soh": 91.2,
    "pack.1.t.1": 26.3,
    "pack.1.t.2": 27.1,
    "pack.1.t.3": 26.8,
    "pack.1.t.4": 27.4,

    "pack.2.v": 389.7,
    "pack.2.i": 8.0,
    "pack.2.soc": 62.2,
    "pack.2.soh": 90.5,
    "pack.2.t.1": 26.0,
    "pack.2.t.2": 26.9,
    "pack.2.t.3": 26.6,
    "pack.2.t.4": 27.0,

    "pack.3.v": 390.4,
    "pack.3.i": 8.3,
    "pack.3.soc": 62.8,
    "pack.3.soh": 89.9,
    "pack.3.t.1": 26.5,
    "pack.3.t.2": 27.3,
    "pack.3.t.3": 27.0,
    "pack.3.t.4": 27.6,

    "pack.4.v": 389.9,
    "pack.4.i": 8.1,
    "pack.4.soc": 61.9,
    "pack.4.soh": 90.8,
    "pack.4.t.1": 25.8,
    "pack.4.t.2": 26.7,
    "pack.4.t.3": 26.4,
    "pack.4.t.4": 26.9
  },
  "series": {
    "series.total_energy": [
      { "t": "00:00", "v": 10 }, { "t": "00:15", "v": 11 }, { "t": "00:30", "v": 12 }, { "t": "00:45", "v": 13 },
      { "t": "01:00", "v": 13 }, { "t": "01:15", "v": 14 }, { "t": "01:30", "v": 14 }, { "t": "01:45", "v": 15 },
      { "t": "02:00", "v": 16 }, { "t": "02:15", "v": 16 }, { "t": "02:30", "v": 17 }, { "t": "02:45", "v": 18 },
      { "t": "03:00", "v": 18 }, { "t": "03:15", "v": 19 }, { "t": "03:30", "v": 20 }, { "t": "03:45", "v": 20 }
    ],
    "series.chg_solar_energy": [
      { "t": "00:00", "v": 0 }, { "t": "00:15", "v": 0 }, { "t": "00:30", "v": 0 }, { "t": "00:45", "v": 0 },
      { "t": "01:00", "v": 0 }, { "t": "01:15", "v": 0 }, { "t": "01:30", "v": 0 }, { "t": "01:45", "v": 0 },
      { "t": "02:00", "v": 0 }, { "t": "02:15", "v": 0 }, { "t": "02:30", "v": 0 }, { "t": "02:45", "v": 0 },
      { "t": "03:00", "v": 0 }, { "t": "03:15", "v": 0 }, { "t": "03:30", "v": 0 }, { "t": "03:45", "v": 0 }
    ],
    "series.chg_grid_energy": [
      { "t": "00:00", "v": 2 }, { "t": "00:15", "v": 2 }, { "t": "00:30", "v": 2 }, { "t": "00:45", "v": 3 },
      { "t": "01:00", "v": 3 }, { "t": "01:15", "v": 3 }, { "t": "01:30", "v": 3 }, { "t": "01:45", "v": 4 },
      { "t": "02:00", "v": 4 }, { "t": "02:15", "v": 4 }, { "t": "02:30", "v": 4 }, { "t": "02:45", "v": 4 },
      { "t": "03:00", "v": 4 }, { "t": "03:15", "v": 5 }, { "t": "03:30", "v": 5 }, { "t": "03:45", "v": 5 }
    ],
    "series.discharged_energy": [
      { "t": "00:00", "v": 0 }, { "t": "00:15", "v": 0 }, { "t": "00:30", "v": 0 }, { "t": "00:45", "v": 0 },
      { "t": "01:00", "v": 0 }, { "t": "01:15", "v": 0 }, { "t": "01:30", "v": 0 }, { "t": "01:45", "v": 0 },
      { "t": "02:00", "v": 0 }, { "t": "02:15", "v": 0 }, { "t": "02:30", "v": 0 }, { "t": "02:45", "v": 0 },
      { "t": "03:00", "v": 0 }, { "t": "03:15", "v": 0 }, { "t": "03:30", "v": 0 }, { "t": "03:45", "v": 0 }
    ],
    "series.temperature_avg": [
      { "t": "00:00", "v": 26.1 }, { "t": "00:15", "v": 26.2 }, { "t": "00:30", "v": 26.2 }, { "t": "00:45", "v": 26.3 },
      { "t": "01:00", "v": 26.4 }, { "t": "01:15", "v": 26.5 }, { "t": "01:30", "v": 26.5 }, { "t": "01:45", "v": 26.6 },
      { "t": "02:00", "v": 26.7 }, { "t": "02:15", "v": 26.7 }, { "t": "02:30", "v": 26.8 }, { "t": "02:45", "v": 26.9 },
      { "t": "03:00", "v": 27.0 }, { "t": "03:15", "v": 27.0 }, { "t": "03:30", "v": 27.1 }, { "t": "03:45", "v": 27.1 }
    ]
  }
}